.setup.cfg.swo
AUTHORS
ChangeLog
LICENSE
README.md
requirements.txt
setup.cfg
setup.py
lluv/__init__.py
lluv/lluv.py
lluv/lluv_classes.py
lluv/lluv_cli.py
lluv/lluv_simple_cli.py
lluv/lluv_tui.py
lluv/lluvconsole.py
lluv/lluvrc
lluv.egg-info/PKG-INFO
lluv.egg-info/SOURCES.txt
lluv.egg-info/dependency_links.txt
lluv.egg-info/entry_points.txt
lluv.egg-info/not-zip-safe
lluv.egg-info/pbr.json
lluv.egg-info/requires.txt
lluv.egg-info/top_level.txt