Metadata-Version: 1.1
Name: lluv
Version: 1.2.6.dev63
Summary: Front end for the linux command DD with a progress bar.
Home-page: UNKNOWN
Author: Jacob Potter
Author-email: jacobpotter7767@gmail.com
License: MIT
Keywords: python
Platform: UNKNOWN
Classifier: Natural Language :: English
Classifier: Operating System :: POSIX :: Linux
Classifier: Programming Language :: Python :: 3.5
